Workbook
Name Selic_Atual_API: APP!$B$11
Name Aporte_Mensal: APP!$C$19
Name Tempo_de_Investimento_Em_Anos: APP!$C$20
Name Selic_Atual_Manipulada: APP!$C$21
Name Selic_Atual_Ano_Manipulada: APP!$C$21
Name Selic_Atual_Ano_API: APP!$B$11
Name Patrimonio_Acumulado: APP!$C$23
Name Rendimento_Mensal: APP!$C$24
Name Patrimonio_2_Anos: APP!$C$27
Name Patrimonio_5_Anos: APP!$C$28
Name Patrimonio_10_Anos: APP!$C$29
Name Patrimonio_15_Anos: APP!$C$30
Name Selic_Atual_API: 'Planilha1 (2)'!$B$11
Name Aporte_Mensal: 'Planilha1 (2)'!$C$15
Name Tempo_de_Investimento_Em_Anos: 'Planilha1 (2)'!$C$16
Name Selic_Atual_Manipulada: 'Planilha1 (2)'!$C$17
Name Selic_Atual_Ano_Manipulada: 'Planilha1 (2)'!$C$17
Name Selic_Atual_Ano_API: 'Planilha1 (2)'!$B$11
Name Patrimonio_Acumulado: 'Planilha1 (2)'!$C$19
Name Rendimento_Mensal: 'Planilha1 (2)'!$C$20
Name Patrimonio_2_Anos: 'Planilha1 (2)'!$C$22
Name Patrimonio_5_Anos: 'Planilha1 (2)'!$C$23
Name Patrimonio_10_Anos: 'Planilha1 (2)'!$C$24
Name Patrimonio_15_Anos: 'Planilha1 (2)'!$C$25
Name ExternalData_1: APP!$B$11
Name aporte: [1]APP!$D$17
Name patrimonio: [1]APP!$D$20

Sheet APP
B10: Taxa SELIC do dia: | D10: Fonte: Api BCB
B11: [{"data":"10/09/2026","valor":"13.90"}]
B13: Meu salário mensal | D13: 10000
B14: Sugestão de investimento 30% | D14: =D13*30% -> 3000
B17: Tesouro SELIC
B18: Qual o meu aporte inicial? | D18: 20000
B19: Quanto vou inverstir por mês? | D19: 2000
B20: Por quanto tempo em anos quero investir? | D20: 30
B21: Qual o percentual de juros mensal? | D21: =VALUE(SUBSTITUTE(SUBSTITUTE(SUBSTITUTE(SUBSTITUTE(RIGHT(B11,8),"""",""),"}",""),"]",""),".",","))/100 -> 0.139
B23: Qual será o meu patrimônio acumulado? | D23: =-PV((1+D21)^(1/12)-1,D20*12,D19)+D18 -> 199707.76
B24: Qual será o meu rendimento mensal? | D24: =D23*((1+D21)^(1/12)-1) -> 2177.7972
B26: Tempo em anos | C26: Patrimônio acumulado | D26: Rendimentos
B27: 2 | C27: =-PV((1+D21)^(1/12)-1,B27*12,D19)+D18 -> 62032.54 | D27: =C27*((1+D21)^(1/12)-1) -> 676.45991
B28: 5 | C28: =-PV((1+D21)^(1/12)-1,B28*12,D19)+D18 -> 107730.56 | D28: =C28*((1+D21)^(1/12)-1) -> 1174.7932
B29: 10 | C29: =-PV((1+D21)^(1/12)-1,B29*12,D19)+D18 -> 153495.44 | D29: =C29*((1+D21)^(1/12)-1) -> 1673.8555
B30: 15 | C30: =-PV((1+D21)^(1/12)-1,B30*12,D19)+D18 -> 177368.81 | D30: =C30*((1+D21)^(1/12)-1) -> 1934.1927
B33: Fundos imobiliários - divisão de investimentos
B34: Perfil | D34: Moderado
B35: Aporte mensal | D35: 500
B37: Tipo de FIIs | C37: Percentual Sugerido | D37: Valores
B38: Papel | C38: =VLOOKUP($D$34&"-"&B38,Configuração!$B:$E,4,FALSE) -> 0.32 | D38: =$D$35*C38 -> 160
B39: Tijolo | C39: =VLOOKUP($D$34&"-"&B39,Configuração!$B:$E,4,FALSE) -> 0.35 | D39: =$D$35*C39 -> 175
B40: Híbridos | C40: =VLOOKUP($D$34&"-"&B40,Configuração!$B:$E,4,FALSE) -> 0.08 | D40: =$D$35*C40 -> 40
B41: Fofs | C41: =VLOOKUP($D$34&"-"&B41,Configuração!$B:$E,4,FALSE) -> 0.05 | D41: =$D$35*C41 -> 25
B42: Desenvolvimento | C42: =VLOOKUP($D$34&"-"&B42,Configuração!$B:$E,4,FALSE) -> 0.1 | D42: =$D$35*C42 -> 50
B43: Hotelarias | C43: =VLOOKUP($D$34&"-"&B43,Configuração!$B:$E,4,FALSE) -> 0.1 | D43: =$D$35*C43 -> 50

Sheet Planilha1 (2)
B10: Taxa SELIC do dia: | C10: Fonte: Api BCB
B11: [{"data":"08/09/2026","valor":"13.90"}]
B14: Qual o meu aporte inicial? | C14: 20000 | D14: 20000
B15: Quanto vou inverstir por mês? | C15: 2000 | D15: 2000
B16: Por quantos anos quero investir? | C16: 1 | D16: 1
B17: Qual o percentual de juros mensal? | C17: =VALUE(SUBSTITUTE(SUBSTITUTE(SUBSTITUTE(SUBSTITUTE(RIGHT(B11,8),"""",""),"}",""),"]",""),".",","))/100 -> 0.139 | D17: =VALUE(SUBSTITUTE(SUBSTITUTE(SUBSTITUTE(SUBSTITUTE(RIGHT(B11,8),"""",""),"}",""),"]",""),".",","))/100 -> 0.139
B19: Quanto será o meu patrimônio acumulado? | D19: =-PV((1+D17)^(1/12)-1,D16*12,D15)+D14 -> 42381.984
B20: Qual será meu rendimento mensal? | D20: =D19*((1+D17)^(1/12)-1) -> 462.17215
A22: 2 | B22: Quanto será meu patrimônio em 2 anos? | C22: =-PV((1+C18)^(1/12)-1,A22*12,D15)+D14 -> 68000 | D22: =C22*((1+C17)^(1/12)-1) -> 741.53458
A23: 5 | B23: Quanto será meu patrimônio em 5 anos? | C23: =-PV((1+C17)^(1/12)-1,A23*12,C15)+C14 -> 107730.56 | D23: =C23*((1+C17)^(1/12)-1) -> 1174.7932
A24: 10 | B24: Quanto será meu patrimônio em 10 anos? | C24: =-PV((1+C17)^(1/12)-1,A24*12,C15)+C14 -> 153495.44 | D24: =C24*((1+C17)^(1/12)-1) -> 1673.8555
A25: 15 | B25: Quanto será meu patrimônio em 15 anos? | C25: =-PV((1+C17)^(1/12)-1,A25*12,C15)+C14 -> 177368.81 | D25: =C25*((1+C17)^(1/12)-1) -> 1934.1927

Sheet Configuração
A1: Caminho API | B1: https://api.bcb.gov.br/dados/serie/bcdata.sgs.1178/dados/ultimos/1?formato=json
A5: Perfis | B5: CHAVE | C5: PERFIL | D5: TIPO DE FII | E5: %
A6: Agressivo | B6: =C6&"-"&D6 -> Conservador-PAPEL | C6: Conservador | D6: PAPEL | E6: 0.3
A7: Moderado | B7: =C7&"-"&D7 -> Conservador-TIJOLO | C7: Conservador | D7: TIJOLO | E7: 0.5
A8: Conservador | B8: =C8&"-"&D8 -> Conservador-HÍBRIDOS | C8: Conservador | D8: HÍBRIDOS | E8: 0.1
B9: =C9&"-"&D9 -> Conservador-FOFs | C9: Conservador | D9: FOFs | E9: 0.1
B10: =C10&"-"&D10 -> Conservador-DESENVOLVIMENTO | C10: Conservador | D10: DESENVOLVIMENTO | E10: 0
B11: =C11&"-"&D11 -> Conservador-HOTELARIAS | C11: Conservador | D11: HOTELARIAS | E11: 0
B12: =C12&"-"&D12 -> Moderado-PAPEL | C12: Moderado | D12: PAPEL | E12: 0.32
B13: =C13&"-"&D13 -> Moderado-TIJOLO | C13: Moderado | D13: TIJOLO | E13: 0.35
B14: =C14&"-"&D14 -> Moderado-HÍBRIDOS | C14: Moderado | D14: HÍBRIDOS | E14: 0.08
B15: =C15&"-"&D15 -> Moderado-FOFs | C15: Moderado | D15: FOFs | E15: 0.05
B16: =C16&"-"&D16 -> Moderado-DESENVOLVIMENTO | C16: Moderado | D16: DESENVOLVIMENTO | E16: 0.1
B17: =C17&"-"&D17 -> Moderado-HOTELARIAS | C17: Moderado | D17: HOTELARIAS | E17: 0.1
B18: =C18&"-"&D18 -> Agressivo-PAPEL | C18: Agressivo | D18: PAPEL | E18: 0.5
B19: =C19&"-"&D19 -> Agressivo-TIJOLO | C19: Agressivo | D19: TIJOLO | E19: 0.1
B20: =C20&"-"&D20 -> Agressivo-HÍBRIDOS | C20: Agressivo | D20: HÍBRIDOS | E20: 0.05
... B23: =C23&"-"&D23 -> Agressivo-HOTELARIAS | C23: Agressivo | D23: HOTELARIAS | E23: 0.1
